README.rst
setup.cfg
setup.py
mill/__init__.py
mill/base.py
mill/errors.py
mill/schema.py
mill/data/schema.json
mill_py.egg-info/PKG-INFO
mill_py.egg-info/SOURCES.txt
mill_py.egg-info/dependency_links.txt
mill_py.egg-info/requires.txt
mill_py.egg-info/top_level.txt