Metadata-Version: 1.1
Name: mill-py
Version: 1.0.0
Summary: Python client for interacting with Textile's REST API.
Home-page: https://gitlab.com/weareset/mill-py
Author: Textile
Author-email: carson@textile.io
License: UNKNOWN
Download-URL: https://gitlab.com/textileio/mill-py/repository/1.0.0/archive.tar.gz
Keywords: REST API Textile Data
Platform: UNKNOWN
Classifier: Development Status :: 3 - Alpha
Classifier: Intended Audience :: Developers
Classifier: Intended Audience :: Science/Research
Classifier: License :: OSI Approved :: BSD License
Classifier: Natural Language :: English
Classifier: Operating System :: OS Independent
Classifier: Programming Language :: Python :: 2
Classifier: Programming Language :: Python :: 2.7
Classifier: Programming Language :: Python :: 3
Classifier: Programming Language :: Python :: 3.4
Classifier: Programming Language :: Python :: 3.5
Classifier: Programming Language :: Python :: 3.6
Classifier: Topic :: Scientific/Engineering :: Information Analysis
